directkeys/__init__.py
directkeys/__main__.py
directkeys/_canonical_names.py
directkeys/_darwinkeyboard.py
directkeys/_darwinmouse.py
directkeys/_generic.py
directkeys/_keyboard_event.py
directkeys/_mouse_event.py
directkeys/_nixcommon.py
directkeys/_nixkeyboard.py
directkeys/_nixmouse.py
directkeys/_winkeyboard.py
directkeys/_winmouse.py
directkeys/mouse.py
directkeys-1.0.0.dist-info/licenses/LICENSE.txt
directkeys-1.0.0.dist-info/METADATA
directkeys-1.0.0.dist-info/WHEEL
directkeys-1.0.0.dist-info/top_level.txt
directkeys-1.0.0.dist-info/RECORD
