Metadata-Version: 2.4
Name: directkeys
Version: 1.0.0
Summary: A modern and robust keyboard hooking and simulation library for Windows and Linux, focusing on low-level control.
Home-page: https://github.com/WigoWigo10/keyboard
Author: WigoWigo
Author-email: hiigoor93@gmail.com
License: MIT
Keywords: directkeys keyboard hook simulate hotkey low-level win32 sendinput
Classifier: Development Status :: 4 - Beta
Classifier: License :: OSI Approved :: MIT License
Classifier: Operating System :: Microsoft :: Windows
Classifier: Operating System :: Unix
Classifier: Operating System :: MacOS :: MacOS X
Classifier: Programming Language :: Python :: 3
Classifier: Programming Language :: Python :: 3.8
Classifier: Programming Language :: Python :: 3.9
Classifier: Programming Language :: Python :: 3.10
Classifier: Programming Language :: Python :: 3.11
Classifier: Programming Language :: Python :: 3.12
Classifier: Topic :: Software Development :: Libraries :: Python Modules
Classifier: Topic :: Utilities
License-File: LICENSE.txt
Requires-Dist: pyobjc; sys_platform == "darwin"
Dynamic: author
Dynamic: author-email
Dynamic: classifier
Dynamic: description
Dynamic: description-content-type
Dynamic: home-page
Dynamic: keywords
Dynamic: license
Dynamic: license-file
Dynamic: requires-dist
Dynamic: summary
